odoo/addons/l10n_es_aeat_mod296/README.rst
odoo/addons/l10n_es_aeat_mod296/__init__.py
odoo/addons/l10n_es_aeat_mod296/__manifest__.py
odoo/addons/l10n_es_aeat_mod296/data/aeat.model.export.config.csv
odoo/addons/l10n_es_aeat_mod296/data/aeat.model.export.config.line.csv
odoo/addons/l10n_es_aeat_mod296/data/l10n.es.aeat.map.tax.csv
odoo/addons/l10n_es_aeat_mod296/data/l10n.es.aeat.map.tax.line.csv
odoo/addons/l10n_es_aeat_mod296/data/l10n.es.aeat.map.tax.line.tax.csv
odoo/addons/l10n_es_aeat_mod296/docs/DR296_2017.pdf
odoo/addons/l10n_es_aeat_mod296/docs/instrucciones_296.pdf
odoo/addons/l10n_es_aeat_mod296/docs/register_design_296_2008.pdf
odoo/addons/l10n_es_aeat_mod296/i18n/es.po
odoo/addons/l10n_es_aeat_mod296/i18n/l10n_es_aeat_mod296.pot
odoo/addons/l10n_es_aeat_mod296/models/__init__.py
odoo/addons/l10n_es_aeat_mod296/models/mod296.py
odoo/addons/l10n_es_aeat_mod296/readme/CONFIGURE.md
odoo/addons/l10n_es_aeat_mod296/readme/CONTRIBUTORS.md
odoo/addons/l10n_es_aeat_mod296/readme/DESCRIPTION.md
odoo/addons/l10n_es_aeat_mod296/readme/USAGE.md
odoo/addons/l10n_es_aeat_mod296/security/ir.model.access.csv
odoo/addons/l10n_es_aeat_mod296/security/ir_rule.xml
odoo/addons/l10n_es_aeat_mod296/static/description/icon.png
odoo/addons/l10n_es_aeat_mod296/static/description/icon_source.svg
odoo/addons/l10n_es_aeat_mod296/static/description/index.html
odoo/addons/l10n_es_aeat_mod296/tests/__init__.py
odoo/addons/l10n_es_aeat_mod296/tests/test_l10n_es_aeat_mod296.py
odoo/addons/l10n_es_aeat_mod296/views/mod296_views.xml
odoo_addon_l10n_es_aeat_mod296-18.0.1.0.0.2.dist-info/METADATA
odoo_addon_l10n_es_aeat_mod296-18.0.1.0.0.2.dist-info/WHEEL
odoo_addon_l10n_es_aeat_mod296-18.0.1.0.0.2.dist-info/top_level.txt
odoo_addon_l10n_es_aeat_mod296-18.0.1.0.0.2.dist-info/RECORD
